{
    "Albania": "/m/0jdx",
    "Austria": "/m/0h7x",
    "Beralus": "/m/0163v",
    "Belgium": "/m/0154j",
    "Bulgaria": "/m/015qh",
    "Croatia": "/m/01pj7",
    "Czechia": "/m/01mjq",
    "Denmark": "/g/121p5z1h",
    "Estonia": "/m/02kmm",
    "Finland": "/m/02vzc",
    "France": "/m/0f8l9c",
    "Germany": "/m/0345h",
    "Greece": "/m/035qy",
    "Hungary": "/m/03gj2",
    "Iceland": "/m/03rj0",
    "Ireland": "/m/03rt9",
    "Italy": "/m/03rjj",
    "Latvia": "/m/04g5k",
    "Lithuania": "/m/04gzd",
    "Luxembourg": "/m/04gzd",
    "Malta": "/m/04gzd",
    "Monaco": "/m/04w4s",
    "Morocco": "/m/04wgh",
    "Netherlands": "/m/059j2",
    "North Macedonia": "/m/0bjv6",
    "Norway": "/m/05b4w",
    "Poland": "/m/05qhw",
    "Portugal": "/m/05r4w",
    "Romania": "/m/06c1y",
    "Serbia": "/m/077qn",
    "Slovakia": "/m/06npd",
    "Slovenia": "/m/06t8v",
    "Spain": "/m/06mkj",
    "Sweden": "/m/0d0vqn",
    "Switzerland": "/m/06mzp",
    "Tunisia": /m/07fj_",
    "Turkey": "/m/01znc_",
    "United Kingdom": "/m/07ssc",
    "Uzbekistan": "/m/07t_x"
}
