[
    {
        "week": "2026-06-22 to 2026-06-28",
        "combinations": [
            {
                "date": [
                    "2026-06-24",
                    "2026-06-28"
                ],
                "origin": [
                    "HAJ",
                    "AGP"
                ],
                "destination": [
                    "AGP",
                    "LBC"
                ],
                "time": [
                    "05:35",
                    "05:50"
                ],
                "travel_time": [
                    "3 hr 15 min",
                    "3 hr 25 min"
                ],
                "airline": [
                    "Eurowings",
                    "Ryanair"
                ],
                "stops": [
                    "0",
                    "0"
                ],
                "price": [
                    "45",
                    "82"
                ],
                "job": "David",
                "new": false,
                "price_change": 2,
                "total_price": "127"
            },
            {
                "date": [
                    "2026-06-26",
                    "2026-06-28"
                ],
                "origin": [
                    "HAJ",
                    "AGP"
                ],
                "destination": [
                    "AGP",
                    "LBC"
                ],
                "time": [
                    "05:05",
                    "05:50"
                ],
                "travel_time": [
                    "3 hr 15 min",
                    "3 hr 25 min"
                ],
                "airline": [
                    "Eurowings",
                    "Ryanair"
                ],
                "stops": [
                    "0",
                    "0"
                ],
                "price": [
                    "45",
                    "82"
                ],
                "job": "David",
                "new": false,
                "price_change": 2,
                "total_price": "127"
            }
        ]
    },
    {
        "week": "2026-06-29 to 2026-07-05",
        "combinations": [
            {
                "date": [
                    "2026-07-02",
                    "2026-07-05"
                ],
                "origin": [
                    "LBC",
                    "AGP"
                ],
                "destination": [
                    "AGP",
                    "LBC"
                ],
                "time": [
                    "19:15",
                    "05:50"
                ],
                "travel_time": [
                    "3 hr 30 min",
                    "3 hr 25 min"
                ],
                "airline": [
                    "Ryanair",
                    "Ryanair"
                ],
                "stops": [
                    "0",
                    "0"
                ],
                "price": [
                    "99",
                    "35"
                ],
                "job": "David",
                "new": false,
                "price_change": 2,
                "total_price": "134"
            }
        ]
    },
    {
        "week": "2026-08-17 to 2026-08-23",
        "combinations": [
            {
                "date": [
                    "2026-08-20",
                    "2026-08-23"
                ],
                "origin": [
                    "LBC",
                    "AGP"
                ],
                "destination": [
                    "AGP",
                    "LBC"
                ],
                "time": [
                    "19:15",
                    "05:50"
                ],
                "travel_time": [
                    "3 hr 30 min",
                    "3 hr 25 min"
                ],
                "airline": [
                    "Ryanair",
                    "Ryanair"
                ],
                "stops": [
                    "0",
                    "0"
                ],
                "price": [
                    "45",
                    "59"
                ],
                "job": "David",
                "new": false,
                "price_change": 1,
                "total_price": "104"
            },
            {
                "date": [
                    "2026-08-21",
                    "2026-08-23"
                ],
                "origin": [
                    "BRE",
                    "AGP"
                ],
                "destination": [
                    "AGP",
                    "LBC"
                ],
                "time": [
                    "11:10",
                    "05:50"
                ],
                "travel_time": [
                    "3 hr 20 min",
                    "3 hr 25 min"
                ],
                "airline": [
                    "Ryanair",
                    "Ryanair"
                ],
                "stops": [
                    "0",
                    "0"
                ],
                "price": [
                    "47",
                    "59"
                ],
                "job": "David",
                "new": false,
                "price_change": 1,
                "total_price": "106"
            },
            {
                "date": [
                    "2026-08-19",
                    "2026-08-23"
                ],
                "origin": [
                    "HAJ",
                    "AGP"
                ],
                "destination": [
                    "AGP",
                    "LBC"
                ],
                "time": [
                    "05:35",
                    "05:50"
                ],
                "travel_time": [
                    "3 hr 15 min",
                    "3 hr 25 min"
                ],
                "airline": [
                    "Eurowings",
                    "Ryanair"
                ],
                "stops": [
                    "0",
                    "0"
                ],
                "price": [
                    "65",
                    "59"
                ],
                "job": "David",
                "new": false,
                "price_change": 1,
                "total_price": "124"
            },
            {
                "date": [
                    "2026-08-19",
                    "2026-08-23"
                ],
                "origin": [
                    "HAM",
                    "AGP"
                ],
                "destination": [
                    "AGP",
                    "LBC"
                ],
                "time": [
                    "06:10",
                    "05:50"
                ],
                "travel_time": [
                    "3 hr 25 min",
                    "3 hr 25 min"
                ],
                "airline": [
                    "Eurowings",
                    "Ryanair"
                ],
                "stops": [
                    "0",
                    "0"
                ],
                "price": [
                    "65",
                    "59"
                ],
                "job": "David",
                "new": false,
                "price_change": 1,
                "total_price": "124"
            },
            {
                "date": [
                    "2026-08-21",
                    "2026-08-23"
                ],
                "origin": [
                    "HAJ",
                    "AGP"
                ],
                "destination": [
                    "AGP",
                    "LBC"
                ],
                "time": [
                    "05:05",
                    "05:50"
                ],
                "travel_time": [
                    "3 hr 15 min",
                    "3 hr 25 min"
                ],
                "airline": [
                    "Eurowings",
                    "Ryanair"
                ],
                "stops": [
                    "0",
                    "0"
                ],
                "price": [
                    "65",
                    "59"
                ],
                "job": "David",
                "new": false,
                "price_change": 1,
                "total_price": "124"
            },
            {
                "date": [
                    "2026-08-20",
                    "2026-08-23"
                ],
                "origin": [
                    "HAM",
                    "AGP"
                ],
                "destination": [
                    "AGP",
                    "LBC"
                ],
                "time": [
                    "14:35",
                    "05:50"
                ],
                "travel_time": [
                    "3 hr 25 min",
                    "3 hr 25 min"
                ],
                "airline": [
                    "Eurowings",
                    "Ryanair"
                ],
                "stops": [
                    "0",
                    "0"
                ],
                "price": [
                    "80",
                    "59"
                ],
                "job": "David",
                "new": true,
                "price_change": 0,
                "total_price": "139"
            },
            {
                "date": [
                    "2026-08-20",
                    "2026-08-24"
                ],
                "origin": [
                    "LBC",
                    "AGP"
                ],
                "destination": [
                    "AGP",
                    "HAM"
                ],
                "time": [
                    "19:15",
                    "18:55"
                ],
                "travel_time": [
                    "3 hr 30 min",
                    "3 hr 15 min"
                ],
                "airline": [
                    "Ryanair",
                    "Eurowings"
                ],
                "stops": [
                    "0",
                    "0"
                ],
                "price": [
                    "45",
                    "95"
                ],
                "job": "David",
                "new": false,
                "price_change": 1,
                "total_price": "140"
            },
            {
                "date": [
                    "2026-08-21",
                    "2026-08-24"
                ],
                "origin": [
                    "BRE",
                    "AGP"
                ],
                "destination": [
                    "AGP",
                    "HAM"
                ],
                "time": [
                    "11:10",
                    "18:55"
                ],
                "travel_time": [
                    "3 hr 20 min",
                    "3 hr 15 min"
                ],
                "airline": [
                    "Ryanair",
                    "Eurowings"
                ],
                "stops": [
                    "0",
                    "0"
                ],
                "price": [
                    "47",
                    "95"
                ],
                "job": "David",
                "new": true,
                "price_change": 0,
                "total_price": "142"
            },
            {
                "date": [
                    "2026-08-21",
                    "2026-08-23"
                ],
                "origin": [
                    "AGP",
                    "LBC"
                ],
                "destination": [
                    "BRE",
                    "AGP"
                ],
                "time": [
                    "07:35",
                    "09:40"
                ],
                "travel_time": [
                    "3 hr 10 min",
                    "3 hr 30 min"
                ],
                "airline": [
                    "Ryanair",
                    "Ryanair"
                ],
                "stops": [
                    "0",
                    "0"
                ],
                "price": [
                    "66",
                    "77"
                ],
                "job": "Pilar",
                "new": false,
                "price_change": 1,
                "total_price": "143"
            }
        ]
    },
    {
        "week": "2026-08-24 to 2026-08-30",
        "combinations": [
            {
                "date": [
                    "2026-08-27",
                    "2026-08-30"
                ],
                "origin": [
                    "LBC",
                    "AGP"
                ],
                "destination": [
                    "AGP",
                    "LBC"
                ],
                "time": [
                    "19:15",
                    "05:50"
                ],
                "travel_time": [
                    "3 hr 30 min",
                    "3 hr 25 min"
                ],
                "airline": [
                    "Ryanair",
                    "Ryanair"
                ],
                "stops": [
                    "0",
                    "0"
                ],
                "price": [
                    "42",
                    "58"
                ],
                "job": "David",
                "new": false,
                "price_change": 2,
                "total_price": "100"
            },
            {
                "date": [
                    "2026-08-28",
                    "2026-08-30"
                ],
                "origin": [
                    "BRE",
                    "AGP"
                ],
                "destination": [
                    "AGP",
                    "LBC"
                ],
                "time": [
                    "11:10",
                    "05:50"
                ],
                "travel_time": [
                    "3 hr 20 min",
                    "3 hr 25 min"
                ],
                "airline": [
                    "Ryanair",
                    "Ryanair"
                ],
                "stops": [
                    "0",
                    "0"
                ],
                "price": [
                    "55",
                    "58"
                ],
                "job": "David",
                "new": false,
                "price_change": 1,
                "total_price": "113"
            }
        ]
    }
]