[
    {
        "week": "2025-10-20 to 2025-10-26",
        "combinations": [
            {
                "date": [
                    "2025-10-24",
                    "2025-10-26"
                ],
                "origin": [
                    "AGP",
                    "LBC"
                ],
                "destination": [
                    "LBC",
                    "AGP"
                ],
                "time": [
                    "06:55",
                    "19:20"
                ],
                "travel_time": [
                    "3 hr 25 min",
                    "3 hr 30 min"
                ],
                "airline": [
                    "Ryanair",
                    "Ryanair"
                ],
                "stops": [
                    "0",
                    "0"
                ],
                "price": [
                    "104",
                    "39"
                ],
                "job": "Pilar",
                "new": false,
                "new_price": false,
                "total_price": "143"
            }
        ]
    },
    {
        "week": "2025-11-03 to 2025-11-09",
        "combinations": [
            {
                "date": [
                    "2025-11-06",
                    "2025-11-10"
                ],
                "origin": [
                    "BRE",
                    "MAD"
                ],
                "destination": [
                    "AGP",
                    "HAM"
                ],
                "time": [
                    "20:35",
                    "19:45"
                ],
                "travel_time": [
                    "3 hr 15 min",
                    "2 hr 55 min"
                ],
                "airline": [
                    "Ryanair",
                    "Iberia"
                ],
                "stops": [
                    "0",
                    "0"
                ],
                "price": [
                    "33",
                    "78"
                ],
                "job": "David",
                "new": false,
                "new_price": true,
                "total_price": "111"
            },
            {
                "date": [
                    "2025-11-05",
                    "2025-11-10"
                ],
                "origin": [
                    "LBC",
                    "MAD"
                ],
                "destination": [
                    "AGP",
                    "HAM"
                ],
                "time": [
                    "19:45",
                    "19:45"
                ],
                "travel_time": [
                    "3 hr 30 min",
                    "2 hr 55 min"
                ],
                "airline": [
                    "Ryanair",
                    "Iberia"
                ],
                "stops": [
                    "0",
                    "0"
                ],
                "price": [
                    "34",
                    "78"
                ],
                "job": "David",
                "new": false,
                "new_price": false,
                "total_price": "112"
            },
            {
                "date": [
                    "2025-11-05",
                    "2025-11-10"
                ],
                "origin": [
                    "BRE",
                    "MAD"
                ],
                "destination": [
                    "AGP",
                    "HAM"
                ],
                "time": [
                    "11:40",
                    "19:45"
                ],
                "travel_time": [
                    "3 hr 15 min",
                    "2 hr 55 min"
                ],
                "airline": [
                    "Ryanair",
                    "Iberia"
                ],
                "stops": [
                    "0",
                    "0"
                ],
                "price": [
                    "45",
                    "78"
                ],
                "job": "David",
                "new": false,
                "new_price": false,
                "total_price": "123"
            },
            {
                "date": [
                    "2025-11-06",
                    "2025-11-09"
                ],
                "origin": [
                    "BRE",
                    "MAD"
                ],
                "destination": [
                    "AGP",
                    "HAM"
                ],
                "time": [
                    "20:35",
                    "19:45"
                ],
                "travel_time": [
                    "3 hr 15 min",
                    "2 hr 55 min"
                ],
                "airline": [
                    "Ryanair",
                    "Iberia"
                ],
                "stops": [
                    "0",
                    "0"
                ],
                "price": [
                    "33",
                    "102"
                ],
                "job": "David",
                "new": false,
                "new_price": true,
                "total_price": "135"
            },
            {
                "date": [
                    "2025-11-05",
                    "2025-11-09"
                ],
                "origin": [
                    "LBC",
                    "MAD"
                ],
                "destination": [
                    "AGP",
                    "HAM"
                ],
                "time": [
                    "19:45",
                    "19:45"
                ],
                "travel_time": [
                    "3 hr 30 min",
                    "2 hr 55 min"
                ],
                "airline": [
                    "Ryanair",
                    "Iberia"
                ],
                "stops": [
                    "0",
                    "0"
                ],
                "price": [
                    "34",
                    "102"
                ],
                "job": "David",
                "new": false,
                "new_price": false,
                "total_price": "136"
            },
            {
                "date": [
                    "2025-11-05",
                    "2025-11-09"
                ],
                "origin": [
                    "BRE",
                    "MAD"
                ],
                "destination": [
                    "AGP",
                    "HAM"
                ],
                "time": [
                    "11:40",
                    "19:45"
                ],
                "travel_time": [
                    "3 hr 15 min",
                    "2 hr 55 min"
                ],
                "airline": [
                    "Ryanair",
                    "Iberia"
                ],
                "stops": [
                    "0",
                    "0"
                ],
                "price": [
                    "45",
                    "102"
                ],
                "job": "David",
                "new": false,
                "new_price": false,
                "total_price": "147"
            }
        ]
    },
    {
        "week": "2025-11-10 to 2025-11-16",
        "combinations": [
            {
                "date": [
                    "2025-11-12",
                    "2025-11-16"
                ],
                "origin": [
                    "LBC",
                    "MAD"
                ],
                "destination": [
                    "AGP",
                    "HAM"
                ],
                "time": [
                    "19:45",
                    "12:15"
                ],
                "travel_time": [
                    "3 hr 30 min",
                    "3 hr"
                ],
                "airline": [
                    "Ryanair",
                    "Iberia"
                ],
                "stops": [
                    "0",
                    "0"
                ],
                "price": [
                    "34",
                    "89"
                ],
                "job": "David",
                "new": false,
                "new_price": false,
                "total_price": "123"
            },
            {
                "date": [
                    "2025-11-12",
                    "2025-11-16"
                ],
                "origin": [
                    "LBC",
                    "MAD"
                ],
                "destination": [
                    "AGP",
                    "HAM"
                ],
                "time": [
                    "19:45",
                    "19:45"
                ],
                "travel_time": [
                    "3 hr 30 min",
                    "2 hr 55 min"
                ],
                "airline": [
                    "Ryanair",
                    "Iberia"
                ],
                "stops": [
                    "0",
                    "0"
                ],
                "price": [
                    "34",
                    "89"
                ],
                "job": "David",
                "new": false,
                "new_price": false,
                "total_price": "123"
            },
            {
                "date": [
                    "2025-11-12",
                    "2025-11-16"
                ],
                "origin": [
                    "LBC",
                    "AGP"
                ],
                "destination": [
                    "AGP",
                    "LBC"
                ],
                "time": [
                    "19:45",
                    "15:25"
                ],
                "travel_time": [
                    "3 hr 30 min",
                    "3 hr 30 min"
                ],
                "airline": [
                    "Ryanair",
                    "Ryanair"
                ],
                "stops": [
                    "0",
                    "0"
                ],
                "price": [
                    "34",
                    "96"
                ],
                "job": "David",
                "new": false,
                "new_price": true,
                "total_price": "130"
            },
            {
                "date": [
                    "2025-11-13",
                    "2025-11-16"
                ],
                "origin": [
                    "BRE",
                    "MAD"
                ],
                "destination": [
                    "AGP",
                    "HAM"
                ],
                "time": [
                    "20:35",
                    "12:15"
                ],
                "travel_time": [
                    "3 hr 15 min",
                    "3 hr"
                ],
                "airline": [
                    "Ryanair",
                    "Iberia"
                ],
                "stops": [
                    "0",
                    "0"
                ],
                "price": [
                    "41",
                    "89"
                ],
                "job": "David",
                "new": false,
                "new_price": false,
                "total_price": "130"
            },
            {
                "date": [
                    "2025-11-13",
                    "2025-11-16"
                ],
                "origin": [
                    "BRE",
                    "MAD"
                ],
                "destination": [
                    "AGP",
                    "HAM"
                ],
                "time": [
                    "20:35",
                    "19:45"
                ],
                "travel_time": [
                    "3 hr 15 min",
                    "2 hr 55 min"
                ],
                "airline": [
                    "Ryanair",
                    "Iberia"
                ],
                "stops": [
                    "0",
                    "0"
                ],
                "price": [
                    "41",
                    "89"
                ],
                "job": "David",
                "new": false,
                "new_price": false,
                "total_price": "130"
            },
            {
                "date": [
                    "2025-11-13",
                    "2025-11-16"
                ],
                "origin": [
                    "BRE",
                    "AGP"
                ],
                "destination": [
                    "AGP",
                    "LBC"
                ],
                "time": [
                    "20:35",
                    "15:25"
                ],
                "travel_time": [
                    "3 hr 15 min",
                    "3 hr 30 min"
                ],
                "airline": [
                    "Ryanair",
                    "Ryanair"
                ],
                "stops": [
                    "0",
                    "0"
                ],
                "price": [
                    "41",
                    "96"
                ],
                "job": "David",
                "new": false,
                "new_price": true,
                "total_price": "137"
            },
            {
                "date": [
                    "2025-11-12",
                    "2025-11-16"
                ],
                "origin": [
                    "HAM",
                    "MAD"
                ],
                "destination": [
                    "AGP",
                    "HAM"
                ],
                "time": [
                    "07:20",
                    "12:15"
                ],
                "travel_time": [
                    "3 hr 20 min",
                    "3 hr"
                ],
                "airline": [
                    "Eurowings",
                    "Iberia"
                ],
                "stops": [
                    "0",
                    "0"
                ],
                "price": [
                    "55",
                    "89"
                ],
                "job": "David",
                "new": false,
                "new_price": false,
                "total_price": "144"
            },
            {
                "date": [
                    "2025-11-12",
                    "2025-11-16"
                ],
                "origin": [
                    "HAM",
                    "MAD"
                ],
                "destination": [
                    "AGP",
                    "HAM"
                ],
                "time": [
                    "07:20",
                    "19:45"
                ],
                "travel_time": [
                    "3 hr 20 min",
                    "2 hr 55 min"
                ],
                "airline": [
                    "Eurowings",
                    "Iberia"
                ],
                "stops": [
                    "0",
                    "0"
                ],
                "price": [
                    "55",
                    "89"
                ],
                "job": "David",
                "new": false,
                "new_price": false,
                "total_price": "144"
            }
        ]
    },
    {
        "week": "2025-11-17 to 2025-11-23",
        "combinations": [
            {
                "date": [
                    "2025-11-19",
                    "2025-11-24"
                ],
                "origin": [
                    "LBC",
                    "MAD"
                ],
                "destination": [
                    "AGP",
                    "HAM"
                ],
                "time": [
                    "19:45",
                    "19:45"
                ],
                "travel_time": [
                    "3 hr 30 min",
                    "2 hr 55 min"
                ],
                "airline": [
                    "Ryanair",
                    "Iberia"
                ],
                "stops": [
                    "0",
                    "0"
                ],
                "price": [
                    "34",
                    "68"
                ],
                "job": "David",
                "new": false,
                "new_price": false,
                "total_price": "102"
            },
            {
                "date": [
                    "2025-11-20",
                    "2025-11-24"
                ],
                "origin": [
                    "BRE",
                    "MAD"
                ],
                "destination": [
                    "AGP",
                    "HAM"
                ],
                "time": [
                    "20:35",
                    "19:45"
                ],
                "travel_time": [
                    "3 hr 15 min",
                    "2 hr 55 min"
                ],
                "airline": [
                    "Ryanair",
                    "Iberia"
                ],
                "stops": [
                    "0",
                    "0"
                ],
                "price": [
                    "34",
                    "68"
                ],
                "job": "David",
                "new": false,
                "new_price": false,
                "total_price": "102"
            },
            {
                "date": [
                    "2025-11-19",
                    "2025-11-24"
                ],
                "origin": [
                    "HAM",
                    "MAD"
                ],
                "destination": [
                    "AGP",
                    "HAM"
                ],
                "time": [
                    "07:20",
                    "19:45"
                ],
                "travel_time": [
                    "3 hr 20 min",
                    "2 hr 55 min"
                ],
                "airline": [
                    "Eurowings",
                    "Iberia"
                ],
                "stops": [
                    "0",
                    "0"
                ],
                "price": [
                    "40",
                    "68"
                ],
                "job": "David",
                "new": false,
                "new_price": false,
                "total_price": "108"
            },
            {
                "date": [
                    "2025-11-19",
                    "2025-11-23"
                ],
                "origin": [
                    "LBC",
                    "MAD"
                ],
                "destination": [
                    "AGP",
                    "HAM"
                ],
                "time": [
                    "19:45",
                    "12:15"
                ],
                "travel_time": [
                    "3 hr 30 min",
                    "3 hr"
                ],
                "airline": [
                    "Ryanair",
                    "Iberia"
                ],
                "stops": [
                    "0",
                    "0"
                ],
                "price": [
                    "34",
                    "84"
                ],
                "job": "David",
                "new": false,
                "new_price": false,
                "total_price": "118"
            },
            {
                "date": [
                    "2025-11-20",
                    "2025-11-23"
                ],
                "origin": [
                    "BRE",
                    "MAD"
                ],
                "destination": [
                    "AGP",
                    "HAM"
                ],
                "time": [
                    "20:35",
                    "12:15"
                ],
                "travel_time": [
                    "3 hr 15 min",
                    "3 hr"
                ],
                "airline": [
                    "Ryanair",
                    "Iberia"
                ],
                "stops": [
                    "0",
                    "0"
                ],
                "price": [
                    "34",
                    "84"
                ],
                "job": "David",
                "new": false,
                "new_price": false,
                "total_price": "118"
            },
            {
                "date": [
                    "2025-11-19",
                    "2025-11-23"
                ],
                "origin": [
                    "LBC",
                    "AGP"
                ],
                "destination": [
                    "AGP",
                    "LBC"
                ],
                "time": [
                    "19:45",
                    "15:25"
                ],
                "travel_time": [
                    "3 hr 30 min",
                    "3 hr 30 min"
                ],
                "airline": [
                    "Ryanair",
                    "Ryanair"
                ],
                "stops": [
                    "0",
                    "0"
                ],
                "price": [
                    "34",
                    "86"
                ],
                "job": "David",
                "new": false,
                "new_price": false,
                "total_price": "120"
            },
            {
                "date": [
                    "2025-11-20",
                    "2025-11-23"
                ],
                "origin": [
                    "BRE",
                    "AGP"
                ],
                "destination": [
                    "AGP",
                    "LBC"
                ],
                "time": [
                    "20:35",
                    "15:25"
                ],
                "travel_time": [
                    "3 hr 15 min",
                    "3 hr 30 min"
                ],
                "airline": [
                    "Ryanair",
                    "Ryanair"
                ],
                "stops": [
                    "0",
                    "0"
                ],
                "price": [
                    "34",
                    "86"
                ],
                "job": "David",
                "new": false,
                "new_price": false,
                "total_price": "120"
            },
            {
                "date": [
                    "2025-11-19",
                    "2025-11-23"
                ],
                "origin": [
                    "LBC",
                    "MAD"
                ],
                "destination": [
                    "AGP",
                    "HAM"
                ],
                "time": [
                    "19:45",
                    "19:45"
                ],
                "travel_time": [
                    "3 hr 30 min",
                    "2 hr 55 min"
                ],
                "airline": [
                    "Ryanair",
                    "Iberia"
                ],
                "stops": [
                    "0",
                    "0"
                ],
                "price": [
                    "34",
                    "89"
                ],
                "job": "David",
                "new": false,
                "new_price": false,
                "total_price": "123"
            },
            {
                "date": [
                    "2025-11-20",
                    "2025-11-23"
                ],
                "origin": [
                    "BRE",
                    "MAD"
                ],
                "destination": [
                    "AGP",
                    "HAM"
                ],
                "time": [
                    "20:35",
                    "19:45"
                ],
                "travel_time": [
                    "3 hr 15 min",
                    "2 hr 55 min"
                ],
                "airline": [
                    "Ryanair",
                    "Iberia"
                ],
                "stops": [
                    "0",
                    "0"
                ],
                "price": [
                    "34",
                    "89"
                ],
                "job": "David",
                "new": false,
                "new_price": false,
                "total_price": "123"
            },
            {
                "date": [
                    "2025-11-20",
                    "2025-11-24"
                ],
                "origin": [
                    "HAM",
                    "MAD"
                ],
                "destination": [
                    "AGP",
                    "HAM"
                ],
                "time": [
                    "06:00",
                    "19:45"
                ],
                "travel_time": [
                    "3 hr 20 min",
                    "2 hr 55 min"
                ],
                "airline": [
                    "Eurowings",
                    "Iberia"
                ],
                "stops": [
                    "0",
                    "0"
                ],
                "price": [
                    "55",
                    "68"
                ],
                "job": "David",
                "new": false,
                "new_price": false,
                "total_price": "123"
            },
            {
                "date": [
                    "2025-11-19",
                    "2025-11-23"
                ],
                "origin": [
                    "HAM",
                    "MAD"
                ],
                "destination": [
                    "AGP",
                    "HAM"
                ],
                "time": [
                    "07:20",
                    "12:15"
                ],
                "travel_time": [
                    "3 hr 20 min",
                    "3 hr"
                ],
                "airline": [
                    "Eurowings",
                    "Iberia"
                ],
                "stops": [
                    "0",
                    "0"
                ],
                "price": [
                    "40",
                    "84"
                ],
                "job": "David",
                "new": false,
                "new_price": false,
                "total_price": "124"
            },
            {
                "date": [
                    "2025-11-19",
                    "2025-11-23"
                ],
                "origin": [
                    "HAM",
                    "AGP"
                ],
                "destination": [
                    "AGP",
                    "LBC"
                ],
                "time": [
                    "07:20",
                    "15:25"
                ],
                "travel_time": [
                    "3 hr 20 min",
                    "3 hr 30 min"
                ],
                "airline": [
                    "Eurowings",
                    "Ryanair"
                ],
                "stops": [
                    "0",
                    "0"
                ],
                "price": [
                    "40",
                    "86"
                ],
                "job": "David",
                "new": false,
                "new_price": false,
                "total_price": "126"
            },
            {
                "date": [
                    "2025-11-19",
                    "2025-11-24"
                ],
                "origin": [
                    "LBC",
                    "MAD"
                ],
                "destination": [
                    "AGP",
                    "HAM"
                ],
                "time": [
                    "19:45",
                    "12:15"
                ],
                "travel_time": [
                    "3 hr 30 min",
                    "3 hr"
                ],
                "airline": [
                    "Ryanair",
                    "Iberia"
                ],
                "stops": [
                    "0",
                    "0"
                ],
                "price": [
                    "34",
                    "95"
                ],
                "job": "David",
                "new": false,
                "new_price": false,
                "total_price": "129"
            },
            {
                "date": [
                    "2025-11-19",
                    "2025-11-23"
                ],
                "origin": [
                    "HAM",
                    "MAD"
                ],
                "destination": [
                    "AGP",
                    "HAM"
                ],
                "time": [
                    "07:20",
                    "19:45"
                ],
                "travel_time": [
                    "3 hr 20 min",
                    "2 hr 55 min"
                ],
                "airline": [
                    "Eurowings",
                    "Iberia"
                ],
                "stops": [
                    "0",
                    "0"
                ],
                "price": [
                    "40",
                    "89"
                ],
                "job": "David",
                "new": false,
                "new_price": false,
                "total_price": "129"
            },
            {
                "date": [
                    "2025-11-20",
                    "2025-11-24"
                ],
                "origin": [
                    "BRE",
                    "MAD"
                ],
                "destination": [
                    "AGP",
                    "HAM"
                ],
                "time": [
                    "20:35",
                    "12:15"
                ],
                "travel_time": [
                    "3 hr 15 min",
                    "3 hr"
                ],
                "airline": [
                    "Ryanair",
                    "Iberia"
                ],
                "stops": [
                    "0",
                    "0"
                ],
                "price": [
                    "34",
                    "95"
                ],
                "job": "David",
                "new": false,
                "new_price": false,
                "total_price": "129"
            },
            {
                "date": [
                    "2025-11-19",
                    "2025-11-24"
                ],
                "origin": [
                    "HAM",
                    "MAD"
                ],
                "destination": [
                    "AGP",
                    "HAM"
                ],
                "time": [
                    "07:20",
                    "12:15"
                ],
                "travel_time": [
                    "3 hr 20 min",
                    "3 hr"
                ],
                "airline": [
                    "Eurowings",
                    "Iberia"
                ],
                "stops": [
                    "0",
                    "0"
                ],
                "price": [
                    "40",
                    "95"
                ],
                "job": "David",
                "new": false,
                "new_price": false,
                "total_price": "135"
            },
            {
                "date": [
                    "2025-11-19",
                    "2025-11-24"
                ],
                "origin": [
                    "HAM",
                    "MAD"
                ],
                "destination": [
                    "BIO",
                    "HAM"
                ],
                "time": [
                    "11:10",
                    "19:45"
                ],
                "travel_time": [
                    "5 hr 50 min",
                    "2 hr 55 min"
                ],
                "airline": [
                    "VuelingIberia",
                    "Iberia"
                ],
                "stops": [
                    "1",
                    "0"
                ],
                "price": [
                    "67",
                    "68"
                ],
                "job": "David",
                "new": false,
                "new_price": false,
                "total_price": "135"
            },
            {
                "date": [
                    "2025-11-20",
                    "2025-11-23"
                ],
                "origin": [
                    "HAM",
                    "MAD"
                ],
                "destination": [
                    "AGP",
                    "HAM"
                ],
                "time": [
                    "06:00",
                    "12:15"
                ],
                "travel_time": [
                    "3 hr 20 min",
                    "3 hr"
                ],
                "airline": [
                    "Eurowings",
                    "Iberia"
                ],
                "stops": [
                    "0",
                    "0"
                ],
                "price": [
                    "55",
                    "84"
                ],
                "job": "David",
                "new": false,
                "new_price": false,
                "total_price": "139"
            },
            {
                "date": [
                    "2025-11-20",
                    "2025-11-23"
                ],
                "origin": [
                    "HAM",
                    "AGP"
                ],
                "destination": [
                    "AGP",
                    "LBC"
                ],
                "time": [
                    "06:00",
                    "15:25"
                ],
                "travel_time": [
                    "3 hr 20 min",
                    "3 hr 30 min"
                ],
                "airline": [
                    "Eurowings",
                    "Ryanair"
                ],
                "stops": [
                    "0",
                    "0"
                ],
                "price": [
                    "55",
                    "86"
                ],
                "job": "David",
                "new": false,
                "new_price": false,
                "total_price": "141"
            },
            {
                "date": [
                    "2025-11-20",
                    "2025-11-23"
                ],
                "origin": [
                    "HAM",
                    "MAD"
                ],
                "destination": [
                    "AGP",
                    "HAM"
                ],
                "time": [
                    "06:00",
                    "19:45"
                ],
                "travel_time": [
                    "3 hr 20 min",
                    "2 hr 55 min"
                ],
                "airline": [
                    "Eurowings",
                    "Iberia"
                ],
                "stops": [
                    "0",
                    "0"
                ],
                "price": [
                    "55",
                    "89"
                ],
                "job": "David",
                "new": false,
                "new_price": false,
                "total_price": "144"
            },
            {
                "date": [
                    "2025-11-19",
                    "2025-11-24"
                ],
                "origin": [
                    "HAM",
                    "MAD"
                ],
                "destination": [
                    "MAD",
                    "HAM"
                ],
                "time": [
                    "07:00",
                    "19:45"
                ],
                "travel_time": [
                    "3 hr",
                    "2 hr 55 min"
                ],
                "airline": [
                    "Iberia",
                    "Iberia"
                ],
                "stops": [
                    "0",
                    "0"
                ],
                "price": [
                    "81",
                    "68"
                ],
                "job": "David",
                "new": false,
                "new_price": false,
                "total_price": "149"
            },
            {
                "date": [
                    "2025-11-20",
                    "2025-11-24"
                ],
                "origin": [
                    "HAM",
                    "MAD"
                ],
                "destination": [
                    "AGP",
                    "HAM"
                ],
                "time": [
                    "06:00",
                    "12:15"
                ],
                "travel_time": [
                    "3 hr 20 min",
                    "3 hr"
                ],
                "airline": [
                    "Eurowings",
                    "Iberia"
                ],
                "stops": [
                    "0",
                    "0"
                ],
                "price": [
                    "55",
                    "95"
                ],
                "job": "David",
                "new": false,
                "new_price": false,
                "total_price": "150"
            },
            {
                "date": [
                    "2025-11-21",
                    "2025-11-23"
                ],
                "origin": [
                    "GRX",
                    "LBC"
                ],
                "destination": [
                    "HAM",
                    "AGP"
                ],
                "time": [
                    "14:25",
                    "19:20"
                ],
                "travel_time": [
                    "5 hr 35 min",
                    "3 hr 30 min"
                ],
                "airline": [
                    "Vueling",
                    "Ryanair"
                ],
                "stops": [
                    "1",
                    "0"
                ],
                "price": [
                    "101",
                    "33"
                ],
                "job": "Pilar",
                "new": false,
                "new_price": false,
                "total_price": "134"
            }
        ]
    },
    {
        "week": "2025-11-24 to 2025-11-30",
        "combinations": [
            {
                "date": [
                    "2025-11-26",
                    "2025-12-01"
                ],
                "origin": [
                    "LBC",
                    "MAD"
                ],
                "destination": [
                    "AGP",
                    "HAM"
                ],
                "time": [
                    "19:45",
                    "19:45"
                ],
                "travel_time": [
                    "3 hr 30 min",
                    "2 hr 55 min"
                ],
                "airline": [
                    "Ryanair",
                    "Iberia"
                ],
                "stops": [
                    "0",
                    "0"
                ],
                "price": [
                    "33",
                    "68"
                ],
                "job": "David",
                "new": false,
                "new_price": false,
                "total_price": "101"
            },
            {
                "date": [
                    "2025-11-27",
                    "2025-12-01"
                ],
                "origin": [
                    "BRE",
                    "MAD"
                ],
                "destination": [
                    "AGP",
                    "HAM"
                ],
                "time": [
                    "20:35",
                    "19:45"
                ],
                "travel_time": [
                    "3 hr 15 min",
                    "2 hr 55 min"
                ],
                "airline": [
                    "Ryanair",
                    "Iberia"
                ],
                "stops": [
                    "0",
                    "0"
                ],
                "price": [
                    "34",
                    "68"
                ],
                "job": "David",
                "new": false,
                "new_price": false,
                "total_price": "102"
            },
            {
                "date": [
                    "2025-11-26",
                    "2025-11-30"
                ],
                "origin": [
                    "LBC",
                    "MAD"
                ],
                "destination": [
                    "AGP",
                    "HAM"
                ],
                "time": [
                    "19:45",
                    "19:45"
                ],
                "travel_time": [
                    "3 hr 30 min",
                    "2 hr 55 min"
                ],
                "airline": [
                    "Ryanair",
                    "Iberia"
                ],
                "stops": [
                    "0",
                    "0"
                ],
                "price": [
                    "33",
                    "89"
                ],
                "job": "David",
                "new": false,
                "new_price": false,
                "total_price": "122"
            },
            {
                "date": [
                    "2025-11-27",
                    "2025-11-30"
                ],
                "origin": [
                    "BRE",
                    "MAD"
                ],
                "destination": [
                    "AGP",
                    "HAM"
                ],
                "time": [
                    "20:35",
                    "19:45"
                ],
                "travel_time": [
                    "3 hr 15 min",
                    "2 hr 55 min"
                ],
                "airline": [
                    "Ryanair",
                    "Iberia"
                ],
                "stops": [
                    "0",
                    "0"
                ],
                "price": [
                    "34",
                    "89"
                ],
                "job": "David",
                "new": false,
                "new_price": false,
                "total_price": "123"
            },
            {
                "date": [
                    "2025-11-26",
                    "2025-11-30"
                ],
                "origin": [
                    "LBC",
                    "AGP"
                ],
                "destination": [
                    "AGP",
                    "LBC"
                ],
                "time": [
                    "19:45",
                    "15:25"
                ],
                "travel_time": [
                    "3 hr 30 min",
                    "3 hr 30 min"
                ],
                "airline": [
                    "Ryanair",
                    "Ryanair"
                ],
                "stops": [
                    "0",
                    "0"
                ],
                "price": [
                    "33",
                    "95"
                ],
                "job": "David",
                "new": false,
                "new_price": true,
                "total_price": "128"
            },
            {
                "date": [
                    "2025-11-27",
                    "2025-11-30"
                ],
                "origin": [
                    "BRE",
                    "AGP"
                ],
                "destination": [
                    "AGP",
                    "LBC"
                ],
                "time": [
                    "20:35",
                    "15:25"
                ],
                "travel_time": [
                    "3 hr 15 min",
                    "3 hr 30 min"
                ],
                "airline": [
                    "Ryanair",
                    "Ryanair"
                ],
                "stops": [
                    "0",
                    "0"
                ],
                "price": [
                    "34",
                    "95"
                ],
                "job": "David",
                "new": false,
                "new_price": true,
                "total_price": "129"
            },
            {
                "date": [
                    "2025-11-26",
                    "2025-12-01"
                ],
                "origin": [
                    "HAM",
                    "MAD"
                ],
                "destination": [
                    "BIO",
                    "HAM"
                ],
                "time": [
                    "11:10",
                    "19:45"
                ],
                "travel_time": [
                    "5 hr 50 min",
                    "2 hr 55 min"
                ],
                "airline": [
                    "VuelingIberia",
                    "Iberia"
                ],
                "stops": [
                    "1",
                    "0"
                ],
                "price": [
                    "69",
                    "68"
                ],
                "job": "David",
                "new": false,
                "new_price": false,
                "total_price": "137"
            },
            {
                "date": [
                    "2025-11-27",
                    "2025-12-01"
                ],
                "origin": [
                    "HAM",
                    "MAD"
                ],
                "destination": [
                    "AGP",
                    "HAM"
                ],
                "time": [
                    "06:00",
                    "19:45"
                ],
                "travel_time": [
                    "3 hr 20 min",
                    "2 hr 55 min"
                ],
                "airline": [
                    "Eurowings",
                    "Iberia"
                ],
                "stops": [
                    "0",
                    "0"
                ],
                "price": [
                    "80",
                    "68"
                ],
                "job": "David",
                "new": false,
                "new_price": false,
                "total_price": "148"
            },
            {
                "date": [
                    "2025-11-26",
                    "2025-12-01"
                ],
                "origin": [
                    "HAM",
                    "MAD"
                ],
                "destination": [
                    "MAD",
                    "HAM"
                ],
                "time": [
                    "07:00",
                    "19:45"
                ],
                "travel_time": [
                    "3 hr",
                    "2 hr 55 min"
                ],
                "airline": [
                    "Iberia",
                    "Iberia"
                ],
                "stops": [
                    "0",
                    "0"
                ],
                "price": [
                    "81",
                    "68"
                ],
                "job": "David",
                "new": false,
                "new_price": false,
                "total_price": "149"
            }
        ]
    },
    {
        "week": "2025-12-01 to 2025-12-07",
        "combinations": [
            {
                "date": [
                    "2025-12-03",
                    "2025-12-07"
                ],
                "origin": [
                    "LBC",
                    "AGP"
                ],
                "destination": [
                    "AGP",
                    "LBC"
                ],
                "time": [
                    "19:45",
                    "15:25"
                ],
                "travel_time": [
                    "3 hr 30 min",
                    "3 hr 30 min"
                ],
                "airline": [
                    "Ryanair",
                    "Ryanair"
                ],
                "stops": [
                    "0",
                    "0"
                ],
                "price": [
                    "35",
                    "48"
                ],
                "job": "David",
                "new": false,
                "new_price": true,
                "total_price": "83"
            },
            {
                "date": [
                    "2025-12-04",
                    "2025-12-07"
                ],
                "origin": [
                    "BRE",
                    "AGP"
                ],
                "destination": [
                    "AGP",
                    "LBC"
                ],
                "time": [
                    "20:35",
                    "15:25"
                ],
                "travel_time": [
                    "3 hr 15 min",
                    "3 hr 30 min"
                ],
                "airline": [
                    "Ryanair",
                    "Ryanair"
                ],
                "stops": [
                    "0",
                    "0"
                ],
                "price": [
                    "40",
                    "48"
                ],
                "job": "David",
                "new": false,
                "new_price": true,
                "total_price": "88"
            },
            {
                "date": [
                    "2025-12-03",
                    "2025-12-07"
                ],
                "origin": [
                    "LBC",
                    "BIO"
                ],
                "destination": [
                    "AGP",
                    "HAM"
                ],
                "time": [
                    "19:45",
                    "14:40"
                ],
                "travel_time": [
                    "3 hr 30 min",
                    "5 hr 20 min"
                ],
                "airline": [
                    "Ryanair",
                    "VuelingIberia"
                ],
                "stops": [
                    "0",
                    "1"
                ],
                "price": [
                    "35",
                    "73"
                ],
                "job": "David",
                "new": false,
                "new_price": true,
                "total_price": "108"
            },
            {
                "date": [
                    "2025-12-04",
                    "2025-12-07"
                ],
                "origin": [
                    "BRE",
                    "BIO"
                ],
                "destination": [
                    "AGP",
                    "HAM"
                ],
                "time": [
                    "20:35",
                    "14:40"
                ],
                "travel_time": [
                    "3 hr 15 min",
                    "5 hr 20 min"
                ],
                "airline": [
                    "Ryanair",
                    "VuelingIberia"
                ],
                "stops": [
                    "0",
                    "1"
                ],
                "price": [
                    "40",
                    "73"
                ],
                "job": "David",
                "new": false,
                "new_price": true,
                "total_price": "113"
            },
            {
                "date": [
                    "2025-12-04",
                    "2025-12-07"
                ],
                "origin": [
                    "HAM",
                    "AGP"
                ],
                "destination": [
                    "BIO",
                    "LBC"
                ],
                "time": [
                    "11:10",
                    "15:25"
                ],
                "travel_time": [
                    "5 hr 50 min",
                    "3 hr 30 min"
                ],
                "airline": [
                    "VuelingIberia",
                    "Ryanair"
                ],
                "stops": [
                    "1",
                    "0"
                ],
                "price": [
                    "72",
                    "48"
                ],
                "job": "David",
                "new": false,
                "new_price": true,
                "total_price": "120"
            },
            {
                "date": [
                    "2025-12-03",
                    "2025-12-07"
                ],
                "origin": [
                    "LBC",
                    "MAD"
                ],
                "destination": [
                    "AGP",
                    "HAM"
                ],
                "time": [
                    "19:45",
                    "13:05"
                ],
                "travel_time": [
                    "3 hr 30 min",
                    "4 hr 50 min"
                ],
                "airline": [
                    "Ryanair",
                    "KLM"
                ],
                "stops": [
                    "0",
                    "1"
                ],
                "price": [
                    "35",
                    "94"
                ],
                "job": "David",
                "new": false,
                "new_price": true,
                "total_price": "129"
            },
            {
                "date": [
                    "2025-12-03",
                    "2025-12-07"
                ],
                "origin": [
                    "LBC",
                    "MAD"
                ],
                "destination": [
                    "AGP",
                    "HAM"
                ],
                "time": [
                    "19:45",
                    "06:00"
                ],
                "travel_time": [
                    "3 hr 30 min",
                    "4 hr 40 min"
                ],
                "airline": [
                    "Ryanair",
                    "KLM"
                ],
                "stops": [
                    "0",
                    "1"
                ],
                "price": [
                    "35",
                    "94"
                ],
                "job": "David",
                "new": false,
                "new_price": true,
                "total_price": "129"
            },
            {
                "date": [
                    "2025-12-03",
                    "2025-12-07"
                ],
                "origin": [
                    "HAM",
                    "AGP"
                ],
                "destination": [
                    "MAD",
                    "LBC"
                ],
                "time": [
                    "07:00",
                    "15:25"
                ],
                "travel_time": [
                    "3 hr",
                    "3 hr 30 min"
                ],
                "airline": [
                    "Iberia",
                    "Ryanair"
                ],
                "stops": [
                    "0",
                    "0"
                ],
                "price": [
                    "81",
                    "48"
                ],
                "job": "David",
                "new": false,
                "new_price": true,
                "total_price": "129"
            },
            {
                "date": [
                    "2025-12-04",
                    "2025-12-07"
                ],
                "origin": [
                    "HAM",
                    "AGP"
                ],
                "destination": [
                    "MAD",
                    "LBC"
                ],
                "time": [
                    "15:55",
                    "15:25"
                ],
                "travel_time": [
                    "3 hr",
                    "3 hr 30 min"
                ],
                "airline": [
                    "Iberia",
                    "Ryanair"
                ],
                "stops": [
                    "0",
                    "0"
                ],
                "price": [
                    "81",
                    "48"
                ],
                "job": "David",
                "new": false,
                "new_price": true,
                "total_price": "129"
            },
            {
                "date": [
                    "2025-12-04",
                    "2025-12-07"
                ],
                "origin": [
                    "HAM",
                    "AGP"
                ],
                "destination": [
                    "MAD",
                    "LBC"
                ],
                "time": [
                    "07:00",
                    "15:25"
                ],
                "travel_time": [
                    "3 hr",
                    "3 hr 30 min"
                ],
                "airline": [
                    "Iberia",
                    "Ryanair"
                ],
                "stops": [
                    "0",
                    "0"
                ],
                "price": [
                    "81",
                    "48"
                ],
                "job": "David",
                "new": false,
                "new_price": true,
                "total_price": "129"
            },
            {
                "date": [
                    "2025-12-03",
                    "2025-12-07"
                ],
                "origin": [
                    "HAM",
                    "AGP"
                ],
                "destination": [
                    "MAD",
                    "LBC"
                ],
                "time": [
                    "15:55",
                    "15:25"
                ],
                "travel_time": [
                    "3 hr",
                    "3 hr 30 min"
                ],
                "airline": [
                    "Iberia",
                    "Ryanair"
                ],
                "stops": [
                    "0",
                    "0"
                ],
                "price": [
                    "86",
                    "48"
                ],
                "job": "David",
                "new": false,
                "new_price": true,
                "total_price": "134"
            },
            {
                "date": [
                    "2025-12-04",
                    "2025-12-07"
                ],
                "origin": [
                    "BRE",
                    "MAD"
                ],
                "destination": [
                    "AGP",
                    "HAM"
                ],
                "time": [
                    "20:35",
                    "13:05"
                ],
                "travel_time": [
                    "3 hr 15 min",
                    "4 hr 50 min"
                ],
                "airline": [
                    "Ryanair",
                    "KLM"
                ],
                "stops": [
                    "0",
                    "1"
                ],
                "price": [
                    "40",
                    "94"
                ],
                "job": "David",
                "new": false,
                "new_price": true,
                "total_price": "134"
            },
            {
                "date": [
                    "2025-12-04",
                    "2025-12-07"
                ],
                "origin": [
                    "BRE",
                    "MAD"
                ],
                "destination": [
                    "AGP",
                    "HAM"
                ],
                "time": [
                    "20:35",
                    "06:00"
                ],
                "travel_time": [
                    "3 hr 15 min",
                    "4 hr 40 min"
                ],
                "airline": [
                    "Ryanair",
                    "KLM"
                ],
                "stops": [
                    "0",
                    "1"
                ],
                "price": [
                    "40",
                    "94"
                ],
                "job": "David",
                "new": false,
                "new_price": true,
                "total_price": "134"
            },
            {
                "date": [
                    "2025-12-04",
                    "2025-12-07"
                ],
                "origin": [
                    "HAM",
                    "AGP"
                ],
                "destination": [
                    "AGP",
                    "LBC"
                ],
                "time": [
                    "06:00",
                    "15:25"
                ],
                "travel_time": [
                    "3 hr 20 min",
                    "3 hr 30 min"
                ],
                "airline": [
                    "Eurowings",
                    "Ryanair"
                ],
                "stops": [
                    "0",
                    "0"
                ],
                "price": [
                    "95",
                    "48"
                ],
                "job": "David",
                "new": false,
                "new_price": true,
                "total_price": "143"
            },
            {
                "date": [
                    "2025-12-03",
                    "2025-12-07"
                ],
                "origin": [
                    "LBC",
                    "AGP"
                ],
                "destination": [
                    "AGP",
                    "HAM"
                ],
                "time": [
                    "19:45",
                    "19:05"
                ],
                "travel_time": [
                    "3 hr 30 min",
                    "3 hr 20 min"
                ],
                "airline": [
                    "Ryanair",
                    "Eurowings"
                ],
                "stops": [
                    "0",
                    "0"
                ],
                "price": [
                    "35",
                    "110"
                ],
                "job": "David",
                "new": false,
                "new_price": true,
                "total_price": "145"
            },
            {
                "date": [
                    "2025-12-04",
                    "2025-12-07"
                ],
                "origin": [
                    "HAM",
                    "BIO"
                ],
                "destination": [
                    "BIO",
                    "HAM"
                ],
                "time": [
                    "11:10",
                    "14:40"
                ],
                "travel_time": [
                    "5 hr 50 min",
                    "5 hr 20 min"
                ],
                "airline": [
                    "VuelingIberia",
                    "VuelingIberia"
                ],
                "stops": [
                    "1",
                    "1"
                ],
                "price": [
                    "72",
                    "73"
                ],
                "job": "David",
                "new": false,
                "new_price": false,
                "total_price": "145"
            },
            {
                "date": [
                    "2025-12-03",
                    "2025-12-07"
                ],
                "origin": [
                    "HAM",
                    "AGP"
                ],
                "destination": [
                    "BIO",
                    "LBC"
                ],
                "time": [
                    "11:10",
                    "15:25"
                ],
                "travel_time": [
                    "5 hr 50 min",
                    "3 hr 30 min"
                ],
                "airline": [
                    "VuelingIberia",
                    "Ryanair"
                ],
                "stops": [
                    "1",
                    "0"
                ],
                "price": [
                    "99",
                    "48"
                ],
                "job": "David",
                "new": false,
                "new_price": true,
                "total_price": "147"
            },
            {
                "date": [
                    "2025-12-04",
                    "2025-12-07"
                ],
                "origin": [
                    "BRE",
                    "AGP"
                ],
                "destination": [
                    "AGP",
                    "HAM"
                ],
                "time": [
                    "20:35",
                    "19:05"
                ],
                "travel_time": [
                    "3 hr 15 min",
                    "3 hr 20 min"
                ],
                "airline": [
                    "Ryanair",
                    "Eurowings"
                ],
                "stops": [
                    "0",
                    "0"
                ],
                "price": [
                    "40",
                    "110"
                ],
                "job": "David",
                "new": true,
                "new_price": false,
                "total_price": "150"
            }
        ]
    },
    {
        "week": "2025-12-08 to 2025-12-14",
        "combinations": [
            {
                "date": [
                    "2025-12-10",
                    "2025-12-14"
                ],
                "origin": [
                    "LBC",
                    "MAD"
                ],
                "destination": [
                    "AGP",
                    "HAM"
                ],
                "time": [
                    "19:45",
                    "12:15"
                ],
                "travel_time": [
                    "3 hr 30 min",
                    "3 hr"
                ],
                "airline": [
                    "Ryanair",
                    "Iberia"
                ],
                "stops": [
                    "0",
                    "0"
                ],
                "price": [
                    "45",
                    "63"
                ],
                "job": "David",
                "new": false,
                "new_price": true,
                "total_price": "108"
            },
            {
                "date": [
                    "2025-12-10",
                    "2025-12-14"
                ],
                "origin": [
                    "LBC",
                    "MAD"
                ],
                "destination": [
                    "AGP",
                    "HAM"
                ],
                "time": [
                    "19:45",
                    "19:45"
                ],
                "travel_time": [
                    "3 hr 30 min",
                    "2 hr 55 min"
                ],
                "airline": [
                    "Ryanair",
                    "Iberia"
                ],
                "stops": [
                    "0",
                    "0"
                ],
                "price": [
                    "45",
                    "63"
                ],
                "job": "David",
                "new": false,
                "new_price": true,
                "total_price": "108"
            },
            {
                "date": [
                    "2025-12-10",
                    "2025-12-15"
                ],
                "origin": [
                    "LBC",
                    "MAD"
                ],
                "destination": [
                    "AGP",
                    "HAM"
                ],
                "time": [
                    "19:45",
                    "19:45"
                ],
                "travel_time": [
                    "3 hr 30 min",
                    "2 hr 55 min"
                ],
                "airline": [
                    "Ryanair",
                    "Iberia"
                ],
                "stops": [
                    "0",
                    "0"
                ],
                "price": [
                    "45",
                    "63"
                ],
                "job": "David",
                "new": true,
                "new_price": false,
                "total_price": "108"
            },
            {
                "date": [
                    "2025-12-11",
                    "2025-12-14"
                ],
                "origin": [
                    "BRE",
                    "MAD"
                ],
                "destination": [
                    "AGP",
                    "HAM"
                ],
                "time": [
                    "20:35",
                    "12:15"
                ],
                "travel_time": [
                    "3 hr 15 min",
                    "3 hr"
                ],
                "airline": [
                    "Ryanair",
                    "Iberia"
                ],
                "stops": [
                    "0",
                    "0"
                ],
                "price": [
                    "49",
                    "63"
                ],
                "job": "David",
                "new": false,
                "new_price": true,
                "total_price": "112"
            },
            {
                "date": [
                    "2025-12-11",
                    "2025-12-14"
                ],
                "origin": [
                    "BRE",
                    "MAD"
                ],
                "destination": [
                    "AGP",
                    "HAM"
                ],
                "time": [
                    "20:35",
                    "19:45"
                ],
                "travel_time": [
                    "3 hr 15 min",
                    "2 hr 55 min"
                ],
                "airline": [
                    "Ryanair",
                    "Iberia"
                ],
                "stops": [
                    "0",
                    "0"
                ],
                "price": [
                    "49",
                    "63"
                ],
                "job": "David",
                "new": false,
                "new_price": false,
                "total_price": "112"
            },
            {
                "date": [
                    "2025-12-11",
                    "2025-12-15"
                ],
                "origin": [
                    "BRE",
                    "MAD"
                ],
                "destination": [
                    "AGP",
                    "HAM"
                ],
                "time": [
                    "20:35",
                    "19:45"
                ],
                "travel_time": [
                    "3 hr 15 min",
                    "2 hr 55 min"
                ],
                "airline": [
                    "Ryanair",
                    "Iberia"
                ],
                "stops": [
                    "0",
                    "0"
                ],
                "price": [
                    "49",
                    "63"
                ],
                "job": "David",
                "new": true,
                "new_price": false,
                "total_price": "112"
            },
            {
                "date": [
                    "2025-12-10",
                    "2025-12-15"
                ],
                "origin": [
                    "LBC",
                    "MAD"
                ],
                "destination": [
                    "AGP",
                    "HAM"
                ],
                "time": [
                    "19:45",
                    "12:15"
                ],
                "travel_time": [
                    "3 hr 30 min",
                    "3 hr"
                ],
                "airline": [
                    "Ryanair",
                    "Iberia"
                ],
                "stops": [
                    "0",
                    "0"
                ],
                "price": [
                    "45",
                    "73"
                ],
                "job": "David",
                "new": true,
                "new_price": false,
                "total_price": "118"
            },
            {
                "date": [
                    "2025-12-11",
                    "2025-12-15"
                ],
                "origin": [
                    "BRE",
                    "MAD"
                ],
                "destination": [
                    "AGP",
                    "HAM"
                ],
                "time": [
                    "20:35",
                    "12:15"
                ],
                "travel_time": [
                    "3 hr 15 min",
                    "3 hr"
                ],
                "airline": [
                    "Ryanair",
                    "Iberia"
                ],
                "stops": [
                    "0",
                    "0"
                ],
                "price": [
                    "49",
                    "73"
                ],
                "job": "David",
                "new": true,
                "new_price": false,
                "total_price": "122"
            },
            {
                "date": [
                    "2025-12-10",
                    "2025-12-14"
                ],
                "origin": [
                    "LBC",
                    "AGP"
                ],
                "destination": [
                    "AGP",
                    "LBC"
                ],
                "time": [
                    "19:45",
                    "15:25"
                ],
                "travel_time": [
                    "3 hr 30 min",
                    "3 hr 30 min"
                ],
                "airline": [
                    "Ryanair",
                    "Ryanair"
                ],
                "stops": [
                    "0",
                    "0"
                ],
                "price": [
                    "45",
                    "82"
                ],
                "job": "David",
                "new": false,
                "new_price": false,
                "total_price": "127"
            },
            {
                "date": [
                    "2025-12-10",
                    "2025-12-15"
                ],
                "origin": [
                    "LBC",
                    "BIO"
                ],
                "destination": [
                    "AGP",
                    "HAM"
                ],
                "time": [
                    "19:45",
                    "17:20"
                ],
                "travel_time": [
                    "3 hr 30 min",
                    "4 hr 35 min"
                ],
                "airline": [
                    "Ryanair",
                    "KLM"
                ],
                "stops": [
                    "0",
                    "1"
                ],
                "price": [
                    "45",
                    "84"
                ],
                "job": "David",
                "new": true,
                "new_price": false,
                "total_price": "129"
            },
            {
                "date": [
                    "2025-12-11",
                    "2025-12-14"
                ],
                "origin": [
                    "BRE",
                    "AGP"
                ],
                "destination": [
                    "AGP",
                    "LBC"
                ],
                "time": [
                    "20:35",
                    "15:25"
                ],
                "travel_time": [
                    "3 hr 15 min",
                    "3 hr 30 min"
                ],
                "airline": [
                    "Ryanair",
                    "Ryanair"
                ],
                "stops": [
                    "0",
                    "0"
                ],
                "price": [
                    "49",
                    "82"
                ],
                "job": "David",
                "new": false,
                "new_price": true,
                "total_price": "131"
            },
            {
                "date": [
                    "2025-12-11",
                    "2025-12-15"
                ],
                "origin": [
                    "BRE",
                    "BIO"
                ],
                "destination": [
                    "AGP",
                    "HAM"
                ],
                "time": [
                    "20:35",
                    "17:20"
                ],
                "travel_time": [
                    "3 hr 15 min",
                    "4 hr 35 min"
                ],
                "airline": [
                    "Ryanair",
                    "KLM"
                ],
                "stops": [
                    "0",
                    "1"
                ],
                "price": [
                    "49",
                    "84"
                ],
                "job": "David",
                "new": true,
                "new_price": false,
                "total_price": "133"
            },
            {
                "date": [
                    "2025-12-10",
                    "2025-12-14"
                ],
                "origin": [
                    "LBC",
                    "MAD"
                ],
                "destination": [
                    "AGP",
                    "HAM"
                ],
                "time": [
                    "19:45",
                    "13:05"
                ],
                "travel_time": [
                    "3 hr 30 min",
                    "4 hr 50 min"
                ],
                "airline": [
                    "Ryanair",
                    "KLM"
                ],
                "stops": [
                    "0",
                    "1"
                ],
                "price": [
                    "45",
                    "94"
                ],
                "job": "David",
                "new": false,
                "new_price": true,
                "total_price": "139"
            },
            {
                "date": [
                    "2025-12-10",
                    "2025-12-15"
                ],
                "origin": [
                    "LBC",
                    "MAD"
                ],
                "destination": [
                    "AGP",
                    "HAM"
                ],
                "time": [
                    "19:45",
                    "06:00"
                ],
                "travel_time": [
                    "3 hr 30 min",
                    "4 hr 40 min"
                ],
                "airline": [
                    "Ryanair",
                    "KLM"
                ],
                "stops": [
                    "0",
                    "1"
                ],
                "price": [
                    "45",
                    "94"
                ],
                "job": "David",
                "new": true,
                "new_price": false,
                "total_price": "139"
            },
            {
                "date": [
                    "2025-12-10",
                    "2025-12-15"
                ],
                "origin": [
                    "LBC",
                    "MAD"
                ],
                "destination": [
                    "AGP",
                    "HAM"
                ],
                "time": [
                    "19:45",
                    "13:05"
                ],
                "travel_time": [
                    "3 hr 30 min",
                    "4 hr 50 min"
                ],
                "airline": [
                    "Ryanair",
                    "KLM"
                ],
                "stops": [
                    "0",
                    "1"
                ],
                "price": [
                    "45",
                    "94"
                ],
                "job": "David",
                "new": true,
                "new_price": false,
                "total_price": "139"
            },
            {
                "date": [
                    "2025-12-11",
                    "2025-12-14"
                ],
                "origin": [
                    "BRE",
                    "MAD"
                ],
                "destination": [
                    "AGP",
                    "HAM"
                ],
                "time": [
                    "20:35",
                    "13:05"
                ],
                "travel_time": [
                    "3 hr 15 min",
                    "4 hr 50 min"
                ],
                "airline": [
                    "Ryanair",
                    "KLM"
                ],
                "stops": [
                    "0",
                    "1"
                ],
                "price": [
                    "49",
                    "94"
                ],
                "job": "David",
                "new": false,
                "new_price": false,
                "total_price": "143"
            },
            {
                "date": [
                    "2025-12-11",
                    "2025-12-15"
                ],
                "origin": [
                    "BRE",
                    "MAD"
                ],
                "destination": [
                    "AGP",
                    "HAM"
                ],
                "time": [
                    "20:35",
                    "06:00"
                ],
                "travel_time": [
                    "3 hr 15 min",
                    "4 hr 40 min"
                ],
                "airline": [
                    "Ryanair",
                    "KLM"
                ],
                "stops": [
                    "0",
                    "1"
                ],
                "price": [
                    "49",
                    "94"
                ],
                "job": "David",
                "new": true,
                "new_price": false,
                "total_price": "143"
            },
            {
                "date": [
                    "2025-12-11",
                    "2025-12-15"
                ],
                "origin": [
                    "BRE",
                    "MAD"
                ],
                "destination": [
                    "AGP",
                    "HAM"
                ],
                "time": [
                    "20:35",
                    "13:05"
                ],
                "travel_time": [
                    "3 hr 15 min",
                    "4 hr 50 min"
                ],
                "airline": [
                    "Ryanair",
                    "KLM"
                ],
                "stops": [
                    "0",
                    "1"
                ],
                "price": [
                    "49",
                    "94"
                ],
                "job": "David",
                "new": true,
                "new_price": false,
                "total_price": "143"
            },
            {
                "date": [
                    "2025-12-10",
                    "2025-12-14"
                ],
                "origin": [
                    "LBC",
                    "BIO"
                ],
                "destination": [
                    "AGP",
                    "HAM"
                ],
                "time": [
                    "19:45",
                    "17:20"
                ],
                "travel_time": [
                    "3 hr 30 min",
                    "4 hr 35 min"
                ],
                "airline": [
                    "Ryanair",
                    "KLM"
                ],
                "stops": [
                    "0",
                    "1"
                ],
                "price": [
                    "45",
                    "99"
                ],
                "job": "David",
                "new": true,
                "new_price": false,
                "total_price": "144"
            },
            {
                "date": [
                    "2025-12-10",
                    "2025-12-15"
                ],
                "origin": [
                    "LBC",
                    "BIO"
                ],
                "destination": [
                    "AGP",
                    "BRE"
                ],
                "time": [
                    "19:45",
                    "17:20"
                ],
                "travel_time": [
                    "3 hr 30 min",
                    "4 hr 40 min"
                ],
                "airline": [
                    "Ryanair",
                    "KLM"
                ],
                "stops": [
                    "0",
                    "1"
                ],
                "price": [
                    "45",
                    "101"
                ],
                "job": "David",
                "new": true,
                "new_price": false,
                "total_price": "146"
            },
            {
                "date": [
                    "2025-12-11",
                    "2025-12-14"
                ],
                "origin": [
                    "BRE",
                    "BIO"
                ],
                "destination": [
                    "AGP",
                    "HAM"
                ],
                "time": [
                    "20:35",
                    "17:20"
                ],
                "travel_time": [
                    "3 hr 15 min",
                    "4 hr 35 min"
                ],
                "airline": [
                    "Ryanair",
                    "KLM"
                ],
                "stops": [
                    "0",
                    "1"
                ],
                "price": [
                    "49",
                    "99"
                ],
                "job": "David",
                "new": true,
                "new_price": false,
                "total_price": "148"
            },
            {
                "date": [
                    "2025-12-11",
                    "2025-12-14"
                ],
                "origin": [
                    "HAM",
                    "MAD"
                ],
                "destination": [
                    "MAD",
                    "HAM"
                ],
                "time": [
                    "15:55",
                    "12:15"
                ],
                "travel_time": [
                    "3 hr",
                    "3 hr"
                ],
                "airline": [
                    "Iberia",
                    "Iberia"
                ],
                "stops": [
                    "0",
                    "0"
                ],
                "price": [
                    "86",
                    "63"
                ],
                "job": "David",
                "new": true,
                "new_price": false,
                "total_price": "149"
            },
            {
                "date": [
                    "2025-12-11",
                    "2025-12-14"
                ],
                "origin": [
                    "HAM",
                    "MAD"
                ],
                "destination": [
                    "MAD",
                    "HAM"
                ],
                "time": [
                    "15:55",
                    "19:45"
                ],
                "travel_time": [
                    "3 hr",
                    "2 hr 55 min"
                ],
                "airline": [
                    "Iberia",
                    "Iberia"
                ],
                "stops": [
                    "0",
                    "0"
                ],
                "price": [
                    "86",
                    "63"
                ],
                "job": "David",
                "new": false,
                "new_price": false,
                "total_price": "149"
            },
            {
                "date": [
                    "2025-12-11",
                    "2025-12-15"
                ],
                "origin": [
                    "HAM",
                    "MAD"
                ],
                "destination": [
                    "MAD",
                    "HAM"
                ],
                "time": [
                    "15:55",
                    "19:45"
                ],
                "travel_time": [
                    "3 hr",
                    "2 hr 55 min"
                ],
                "airline": [
                    "Iberia",
                    "Iberia"
                ],
                "stops": [
                    "0",
                    "0"
                ],
                "price": [
                    "86",
                    "63"
                ],
                "job": "David",
                "new": true,
                "new_price": false,
                "total_price": "149"
            },
            {
                "date": [
                    "2025-12-11",
                    "2025-12-15"
                ],
                "origin": [
                    "BRE",
                    "BIO"
                ],
                "destination": [
                    "AGP",
                    "BRE"
                ],
                "time": [
                    "20:35",
                    "17:20"
                ],
                "travel_time": [
                    "3 hr 15 min",
                    "4 hr 40 min"
                ],
                "airline": [
                    "Ryanair",
                    "KLM"
                ],
                "stops": [
                    "0",
                    "1"
                ],
                "price": [
                    "49",
                    "101"
                ],
                "job": "David",
                "new": true,
                "new_price": false,
                "total_price": "150"
            }
        ]
    }
]