[
    {
        "week": "2025-09-15 to 2025-09-21",
        "combinations": [
            {
                "date": [
                    "2025-09-20",
                    "2025-09-21"
                ],
                "origin": [
                    "AGP",
                    "FMM"
                ],
                "destination": [
                    "NUE",
                    "AGP"
                ],
                "time": [
                    "14:25",
                    "06:00"
                ],
                "travel_time": [
                    "5 hr 30 min",
                    "2 hr 55 min"
                ],
                "airline": [
                    "VuelingIberia",
                    "Ryanair"
                ],
                "stops": [
                    "1",
                    "0"
                ],
                "price": [
                    "79",
                    "76"
                ],
                "job": "Nos vamos al octokber???",
                "new": false,
                "new_price": false,
                "total_price": "155"
            },
            {
                "date": [
                    "2025-09-18",
                    "2025-09-21"
                ],
                "origin": [
                    "AGP",
                    "FMM"
                ],
                "destination": [
                    "MUC",
                    "AGP"
                ],
                "time": [
                    "07:10",
                    "06:00"
                ],
                "travel_time": [
                    "2 hr 50 min",
                    "2 hr 55 min"
                ],
                "airline": [
                    "Norwegian",
                    "Ryanair"
                ],
                "stops": [
                    "0",
                    "0"
                ],
                "price": [
                    "96",
                    "76"
                ],
                "job": "Nos vamos al octokber???",
                "new": false,
                "new_price": false,
                "total_price": "172"
            },
            {
                "date": [
                    "2025-09-20",
                    "2025-09-21"
                ],
                "origin": [
                    "AGP",
                    "NUE"
                ],
                "destination": [
                    "NUE",
                    "AGP"
                ],
                "time": [
                    "14:25",
                    "19:15"
                ],
                "travel_time": [
                    "5 hr 30 min",
                    "3 hr 5 min"
                ],
                "airline": [
                    "VuelingIberia",
                    "Ryanair"
                ],
                "stops": [
                    "1",
                    "0"
                ],
                "price": [
                    "79",
                    "98"
                ],
                "job": "Nos vamos al octokber???",
                "new": false,
                "new_price": false,
                "total_price": "177"
            }
        ]
    }
]